<?xml version="1.0" encoding="utf-8"?>
<search>
  
  
  
  <entry>
    <title>欢迎来到Heartfirey的博客！</title>
    <link href="/2020/11/01/hello-world/"/>
    <url>/2020/11/01/hello-world/</url>
    
    <content type="html"><![CDATA[<h1 id="Welcome！"><a href="#Welcome！" class="headerlink" title="Welcome！"></a>Welcome！</h1><h2 id="Heartfirey"><a href="#Heartfirey" class="headerlink" title="Heartfirey"></a>Heartfirey</h2><blockquote><p> 目前正在维护的项目：</p></blockquote><blockquote><p>已经停止维护的项目：</p><p>1.Elect Media Control Center</p><p>这是一个多媒体管理系统，本打算融入FluentDesign的设计规范，并添加局域网互联的功能，但是由于时间原因，鸽了鸽了</p><p>2.图书管理系统</p><p>只是暂时停止更细，以后会考虑扩大开发规模并融入更友好的设计，但是，，，先鸽了…</p><p>3.参与开发的其他Space Technology项目，由于工作室解散，这些项目随机废除并不再开源</p><p>4.学生管理系统</p><p>写着玩的。。。</p></blockquote>]]></content>
    
    
    
    <tags>
      
      <tag>Default</tag>
      
    </tags>
    
  </entry>
  
  
  
  
</search>
